eagerx_utility/__init__.py
eagerx_utility/aruco_detector.py
eagerx_utility/camera/__init__.py
eagerx_utility/camera/assets/realsense2_d435.urdf
eagerx_utility/camera/calibration.py
eagerx_utility/camera/enginestates.py
eagerx_utility/camera/objects.py
eagerx_utility/camera/pybullet/enginenodes.py
eagerx_utility/ik/__init__.py
eagerx_utility/ik/node.py
eagerx_utility/overlay/__init__.py
eagerx_utility/overlay/node.py
eagerx_utility/reset/__init__.py
eagerx_utility/reset/node.py
eagerx_utility/safety/__init__.py
eagerx_utility/safety/collision.py
eagerx_utility/safety/node.py
eagerx_utility/safety/workspaces.py
eagerx_utility/solid/__init__.py
eagerx_utility/solid/assets/box.urdf
eagerx_utility/solid/assets/box_goal.urdf
eagerx_utility/solid/assets/can.urdf
eagerx_utility/solid/assets/can_goal.urdf
eagerx_utility/solid/assets/surface.urdf
eagerx_utility/solid/goal.py
eagerx_utility/solid/real/__init__.py
eagerx_utility/solid/real/enginenodes.py
eagerx_utility/solid/real/enginestates.py
eagerx_utility/solid/solid.py
eagerx_utility/solid/yaw_node.py
eagerx_utility/utils.py
eagerx_utility-0.0.3.dist-info/LICENSE
eagerx_utility-0.0.3.dist-info/METADATA
eagerx_utility-0.0.3.dist-info/WHEEL
eagerx_utility-0.0.3.dist-info/RECORD
